{"version": "1.1.0",
 "packagesDir": ".lake/packages",
 "packages":
 [{"url": "https://github.com/leanprover/lean4-cli",
   "type": "git",
   "subDir": null,
   "scope": "",
   "rev": "4f10f47646cb7d5748d6f423f4a07f98f7bbcc9e",
   "name": "Cli",
   "manifestFile": "lake-manifest.json",
   "inputRev": "main",
   "inherited": false,
   "configFile": "lakefile.toml"},
  {"url": "https://github.com/fgdorais/lean4-unicode-basic",
   "type": "git",
   "subDir": null,
   "scope": "",
   "rev": "ff04f5c424e50e23476d3539c7c0cc4956e971ad",
   "name": "UnicodeBasic",
   "manifestFile": "lake-manifest.json",
   "inputRev": "main",
   "inherited": false,
   "configFile": "lakefile.lean"},
  {"url": "https://github.com/dupuisf/BibtexQuery",
   "type": "git",
   "subDir": null,
   "scope": "",
   "rev": "058ada3acad7dd0d55657476bf292c8e02a2f650",
   "name": "BibtexQuery",
   "manifestFile": "lake-manifest.json",
   "inputRev": "master",
   "inherited": false,
   "configFile": "lakefile.toml"},
  {"url": "https://github.com/acmepjz/md4lean",
   "type": "git",
   "subDir": null,
   "scope": "",
   "rev": "7e097e9a076d5fbe48aa39aceee871af0d011101",
   "name": "MD4Lean",
   "manifestFile": "lake-manifest.json",
   "inputRev": "main",
   "inherited": false,
   "configFile": "lakefile.lean"}],
 "name": "«doc-gen4»",
 "lakeDir": ".lake"}
